{
  "MsgCid": {
    "/": "bafy2bzacedodfjkgcw36mgxb6ku5ojsak56t5ed5ktiix4ojrmy6j6ictjy56"
  },
  "Msg": {
    "Version": 0,
    "To": "f02620",
    "From": "f1bvwws3blxcpigqgdvhemfgssdi3u7t4qvhkp3my",
    "Nonce": 4655,
    "Value": "0",
    "GasLimit": 33785410,
    "GasFeeCap": "1183943009",
    "GasPremium": "120829872",
    "Method": 6,
    "Params": "iggZFs7YKlgpAAGC4gOB6AIgMs7Oe7yJwZBxi2wlPSd+MmXM+xTnzzegLL1lkuhp0B8aACmMqYUaAc3wLhoBzh0nGgHOOrYaAc46txoBzjq4GgBBSpf0AAAA",
    "CID": {
      "/": "bafy2bzaceck2666rolpo4enxgdggxsqsvc34mfwsv4bj6u7h73ohqnxdwlt5i"
    }
  },
  "MsgRct": {
    "ExitCode": 0,
    "Return": null,
    "GasUsed": 27058468,
    "EventsRoot": null
  },
  "GasCost": {
    "Message": {
      "/": "bafy2bzaceck2666rolpo4enxgdggxsqsvc34mfwsv4bj6u7h73ohqnxdwlt5i"
    },
    "GasUsed": "27058468",
    "BaseFeeBurn": "6472417555767644",
    "OverEstimationBurn": "239123442615525",
    "MinerPenalty": "0",
    "MinerTip": "4082286765767520",
    "Refund": "29206172211548001",
    "TotalCost": "10793827764150689"
  },
  "ExecutionTrace": {
    "Msg": {
      "From": "f1bvwws3blxcpigqgdvhemfgssdi3u7t4qvhkp3my",
      "To": "f02620",
      "Value": "0",
      "Method": 6,
      "Params": "iggZFs7YKlgpAAGC4gOB6AIgMs7Oe7yJwZBxi2wlPSd+MmXM+xTnzzegLL1lkuhp0B8aACmMqYUaAc3wLhoBzh0nGgHOOrYaAc46txoBzjq4GgBBSpf0AAAA",
      "ParamsCodec": 0
    },
    "MsgRct": {
      "ExitCode": 0,
      "Return": null,
      "ReturnCodec": 0
    },
    "GasCharges": [
      {
        "Name": "OnChainMessage",
        "tg": 834963,
        "cg": 38863,
        "sg": 796100,
        "tt": 0
      },
      {
        "Name": "OnMethodInvocation",
        "tg": 75000,
        "cg": 75000,
        "sg": 0,
        "tt": 0
      },
      {
        "Name": "wasm_memory_init",
        "tg": 471860,
        "cg": 471860,
        "sg": 0,
        "tt": 0
      },
      {
        "Name": "wasm_exec",
        "tg": 576,
        "cg": 576,
        "sg": 0,
        "tt": 0
      },
      {
        "Name": "OnSyscall",
        "tg": 14000,
        "cg": 14000,
        "sg": 0,
        "tt": 0
      },
      {
        "Name": "wasm_exec",
        "tg": 448,
        "cg": 448,
        "sg": 0,
        "tt": 0
      },
      {
        "Name": "OnSyscall",
        "tg": 14000,
        "cg": 14000,
        "sg": 0,
        "tt": 0
      },
      {
        "Name": "OnMessageContext",
        "tg": 0,
        "cg": 0,
        "sg": 0,
        "tt": 0
      },
      {
        "Name": "wasm_exec",
        "tg": 395,
        "cg": 395,
        "sg": 0,
        "tt": 0
      },
      {
        "Name": "OnSyscall",
        "tg": 14000,
        "cg": 14000,
        "sg": 0,
        "tt": 0
      },
      {
        "Name": "OnBlockStat",
        "tg": 0,
        "cg": 0,
        "sg": 0,
        "tt": 0
      },
      {
        "Name": "wasm_exec",
        "tg": 4076,
        "cg": 4076,
        "sg": 0,
        "tt": 0
      },
      {
        "Name": "wasm_memory_grow",
        "tg": 26215,
        "cg": 26215,
        "sg": 0,
        "tt": 0
      },
      {
        "Name": "OnSyscall",
        "tg": 14000,
        "cg": 14000,
        "sg": 0,
        "tt": 0
      },
      {
        "Name": "OnBlockRead",
        "tg": 36,
        "cg": 36,
        "sg": 0,
        "tt": 0
      },
      {
        "Name": "wasm_exec",
        "tg": 18034,
        "cg": 18034,
        "sg": 0,
        "tt": 0
      },
      {
        "Name": "OnSyscall",
        "tg": 14000,
        "cg": 14000,
        "sg": 0,
        "tt": 0
      },
      {
        "Name": "OnGetActorCodeCid",
        "tg": 0,
        "cg": 0,
        "sg": 0,
        "tt": 0
      },
      {
        "Name": "wasm_exec",
        "tg": 9701,
        "cg": 9701,
        "sg": 0,
        "tt": 0
      },
      {
        "Name": "OnSyscall",
        "tg": 14000,
        "cg": 14000,
        "sg": 0,
        "tt": 0
      },
      {
        "Name": "OnGetBuiltinActorType",
        "tg": 0,
        "cg": 0,
        "sg": 0,
        "tt": 0
      },
      {
        "Name": "wasm_exec",
        "tg": 27697,
        "cg": 27697,
        "sg": 0,
        "tt": 0
      },
      {
        "Name": "OnSyscall",
        "tg": 14000,
        "cg": 14000,
        "sg": 0,
        "tt": 0
      },
      {
        "Name": "OnNetworkContext",
        "tg": 0,
        "cg": 0,
        "sg": 0,
        "tt": 0
      },
      {
        "Name": "wasm_exec",
        "tg": 12485,
        "cg": 12485,
        "sg": 0,
        "tt": 0
      },
      {
        "Name": "OnSyscall",
        "tg": 14000,
        "cg": 14000,
        "sg": 0,
        "tt": 0
      },
      {
        "Name": "wasm_exec",
        "tg": 2388,
        "cg": 2388,
        "sg": 0,
        "tt": 0
      },
      {
        "Name": "OnSyscall",
        "tg": 14000,
        "cg": 14000,
        "sg": 0,
        "tt": 0
      },
      {
        "Name": "OnBlockRead",
        "tg": 26,
        "cg": 26,
        "sg": 0,
        "tt": 0
      },
      {
        "Name": "wasm_exec",
        "tg": 38872,
        "cg": 38872,
        "sg": 0,
        "tt": 0
      },
      {
        "Name": "OnSyscall",
        "tg": 14000,
        "cg": 14000,
        "sg": 0,
        "tt": 0
      },
      {
        "Name": "wasm_exec",
        "tg": 2628,
        "cg": 2628,
        "sg": 0,
        "tt": 0
      },
      {
        "Name": "OnSyscall",
        "tg": 14000,
        "cg": 14000,
        "sg": 0,
        "tt": 0
      },
      {
        "Name": "OnBlockRead",
        "tg": 36,
        "cg": 36,
        "sg": 0,
        "tt": 0
      },
      {
        "Name": "wasm_exec",
        "tg": 71802,
        "cg": 71802,
        "sg": 0,
        "tt": 0
      },
      {
        "Name": "OnSyscall",
        "tg": 14000,
        "cg": 14000,
        "sg": 0,
        "tt": 0
      },
      {
        "Name": "OnBlockCreate",
        "tg": 350,
        "cg": 84,
        "sg": 266,
        "tt": 0
      },
      {
        "Name": "wasm_exec",
        "tg": 888,
        "cg": 888,
        "sg": 0,
        "tt": 0
      },
      {
        "Name": "OnSyscall",
        "tg": 14000,
        "cg": 14000,
        "sg": 0,
        "tt": 0
      },
      {
        "Name": "wasm_exec",
        "tg": 2468,
        "cg": 2468,
        "sg": 0,
        "tt": 0
      },
      {
        "Name": "OnSyscall",
        "tg": 14000,
        "cg": 14000,
        "sg": 0,
        "tt": 0
      },
      {
        "Name": "OnBlockRead",
        "tg": 19,
        "cg": 19,
        "sg": 0,
        "tt": 0
      },
      {
        "Name": "wasm_exec",
        "tg": 20341,
        "cg": 20341,
        "sg": 0,
        "tt": 0
      },
      {
        "Name": "OnSyscall",
        "tg": 14000,
        "cg": 14000,
        "sg": 0,
        "tt": 0
      },
      {
        "Name": "wasm_exec",
        "tg": 6482,
        "cg": 6482,
        "sg": 0,
        "tt": 0
      },
      {
        "Name": "OnSyscall",
        "tg": 14000,
        "cg": 14000,
        "sg": 0,
        "tt": 0
      },
      {
        "Name": "OnBlockOpenBase",
        "tg": 187440,
        "cg": 0,
        "sg": 187440,
        "tt": 0
      },
      {
        "Name": "OnBlockOpenPerByte",
        "tg": 3350,
        "cg": 804,
        "sg": 2546,
        "tt": 0
      },
      {
        "Name": "wasm_exec",
        "tg": 1456,
        "cg": 1456,
        "sg": 0,
        "tt": 0
      },
      {
        "Name": "OnSyscall",
        "tg": 14000,
        "cg": 14000,
        "sg": 0,
        "tt": 0
      },
      {
        "Name": "OnBlockRead",
        "tg": 134,
        "cg": 134,
        "sg": 0,
        "tt": 0
      },
      {
        "Name": "wasm_exec",
        "tg": 74320,
        "cg": 74320,
        "sg": 0,
        "tt": 0
      },
      {
        "Name": "OnSyscall",
        "tg": 14000,
        "cg": 14000,
        "sg": 0,
        "tt": 0
      },
      {
        "Name": "OnSelfBalance",
        "tg": 0,
        "cg": 0,
        "sg": 0,
        "tt": 0
      },
      {
        "Name": "wasm_exec",
        "tg": 8785,
        "cg": 8785,
        "sg": 0,
        "tt": 0
      },
      {
        "Name": "OnSyscall",
        "tg": 14000,
        "cg": 14000,
        "sg": 0,
        "tt": 0
      },
      {
        "Name": "OnSelfBalance",
        "tg": 0,
        "cg": 0,
        "sg": 0,
        "tt": 0
      },
      {
        "Name": "wasm_exec",
        "tg": 11708,
        "cg": 11708,
        "sg": 0,
        "tt": 0
      },
      {
        "Name": "OnSyscall",
        "tg": 14000,
        "cg": 14000,
        "sg": 0,
        "tt": 0
      },
      {
        "Name": "OnBlockOpenBase",
        "tg": 187440,
        "cg": 0,
        "sg": 187440,
        "tt": 0
      },
      {
        "Name": "OnBlockOpenPerByte",
        "tg": 1090,
        "cg": 262,
        "sg": 829,
        "tt": 0
      },
      {
        "Name": "wasm_exec",
        "tg": 1112,
        "cg": 1112,
        "sg": 0,
        "tt": 0
      },
      {
        "Name": "OnSyscall",
        "tg": 14000,
        "cg": 14000,
        "sg": 0,
        "tt": 0
      },
      {
        "Name": "OnBlockRead",
        "tg": 44,
        "cg": 44,
        "sg": 0,
        "tt": 0
      },
      {
        "Name": "wasm_exec",
        "tg": 882084,
        "cg": 882084,
        "sg": 0,
        "tt": 0
      },
      {
        "Name": "OnSyscall",
        "tg": 14000,
        "cg": 14000,
        "sg": 0,
        "tt": 0
      },
      {
        "Name": "OnBlockOpenBase",
        "tg": 187440,
        "cg": 0,
        "sg": 187440,
        "tt": 0
      },
      {
        "Name": "OnBlockOpenPerByte",
        "tg": 1500,
        "cg": 360,
        "sg": 1140,
        "tt": 0
      },
      {
        "Name": "wasm_exec",
        "tg": 2208,
        "cg": 2208,
        "sg": 0,
        "tt": 0
      },
      {
        "Name": "OnSyscall",
        "tg": 14000,
        "cg": 14000,
        "sg": 0,
        "tt": 0
      },
      {
        "Name": "OnBlockRead",
        "tg": 60,
        "cg": 60,
        "sg": 0,
        "tt": 0
      },
      {
        "Name": "wasm_exec",
        "tg": 1078896,
        "cg": 1078896,
        "sg": 0,
        "tt": 0
      },
      {
        "Name": "OnSyscall",
        "tg": 14000,
        "cg": 14000,
        "sg": 0,
        "tt": 0
      },
      {
        "Name": "OnBlockCreate",
        "tg": 1500,
        "cg": 360,
        "sg": 1140,
        "tt": 0
      },
      {
        "Name": "wasm_exec",
        "tg": 152,
        "cg": 152,
        "sg": 0,
        "tt": 0
      },
      {
        "Name": "OnSyscall",
        "tg": 14000,
        "cg": 14000,
        "sg": 0,
        "tt": 0
      },
      {
        "Name": "OnBlockLink",
        "tg": 1008860,
        "cg": 1860,
        "sg": 1007000,
        "tt": 0
      },
      {
        "Name": "wasm_exec",
        "tg": 10421,
        "cg": 10421,
        "sg": 0,
        "tt": 0
      },
      {
        "Name": "OnSyscall",
        "tg": 14000,
        "cg": 14000,
        "sg": 0,
        "tt": 0
      },
      {
        "Name": "OnBlockOpenBase",
        "tg": 187440,
        "cg": 0,
        "sg": 187440,
        "tt": 0
      },
      {
        "Name": "OnBlockOpenPerByte",
        "tg": 30,
        "cg": 8,
        "sg": 23,
        "tt": 0
      },
      {
        "Name": "wasm_exec",
        "tg": 1256,
        "cg": 1256,
        "sg": 0,
        "tt": 0
      },
      {
        "Name": "OnSyscall",
        "tg": 14000,
        "cg": 14000,
        "sg": 0,
        "tt": 0
      },
      {
        "Name": "OnBlockRead",
        "tg": 2,
        "cg": 2,
        "sg": 0,
        "tt": 0
      },
      {
        "Name": "wasm_exec",
        "tg": 13160,
        "cg": 13160,
        "sg": 0,
        "tt": 0
      },
      {
        "Name": "OnSyscall",
        "tg": 14000,
        "cg": 14000,
        "sg": 0,
        "tt": 0
      },
      {
        "Name": "OnHashing",
        "tg": 14,
        "cg": 14,
        "sg": 0,
        "tt": 0
      },
      {
        "Name": "wasm_exec",
        "tg": 72667,
        "cg": 72667,
        "sg": 0,
        "tt": 0
      },
      {
        "Name": "OnSyscall",
        "tg": 14000,
        "cg": 14000,
        "sg": 0,
        "tt": 0
      },
      {
        "Name": "OnBlockCreate",
        "tg": 1550,
        "cg": 372,
        "sg": 1178,
        "tt": 0
      },
      {
        "Name": "wasm_exec",
        "tg": 152,
        "cg": 152,
        "sg": 0,
        "tt": 0
      },
      {
        "Name": "OnSyscall",
        "tg": 14000,
        "cg": 14000,
        "sg": 0,
        "tt": 0
      },
      {
        "Name": "OnBlockLink",
        "tg": 1025622,
        "cg": 1922,
        "sg": 1023700,
        "tt": 0
      },
      {
        "Name": "wasm_exec",
        "tg": 16106,
        "cg": 16106,
        "sg": 0,
        "tt": 0
      },
      {
        "Name": "OnSyscall",
        "tg": 14000,
        "cg": 14000,
        "sg": 0,
        "tt": 0
      },
      {
        "Name": "OnBlockOpenBase",
        "tg": 187440,
        "cg": 0,
        "sg": 187440,
        "tt": 0
      },
      {
        "Name": "OnBlockOpenPerByte",
        "tg": 600,
        "cg": 144,
        "sg": 456,
        "tt": 0
      },
      {
        "Name": "wasm_exec",
        "tg": 1448,
        "cg": 1448,
        "sg": 0,
        "tt": 0
      },
      {
        "Name": "OnSyscall",
        "tg": 14000,
        "cg": 14000,
        "sg": 0,
        "tt": 0
      },
      {
        "Name": "OnBlockRead",
        "tg": 24,
        "cg": 24,
        "sg": 0,
        "tt": 0
      },
      {
        "Name": "wasm_exec",
        "tg": 43220,
        "cg": 43220,
        "sg": 0,
        "tt": 0
      },
      {
        "Name": "OnSyscall",
        "tg": 14000,
        "cg": 14000,
        "sg": 0,
        "tt": 0
      },
      {
        "Name": "OnBlockOpenBase",
        "tg": 187440,
        "cg": 0,
        "sg": 187440,
        "tt": 0
      },
      {
        "Name": "OnBlockOpenPerByte",
        "tg": 6140,
        "cg": 1474,
        "sg": 4667,
        "tt": 0
      },
      {
        "Name": "wasm_exec",
        "tg": 3132,
        "cg": 3132,
        "sg": 0,
        "tt": 0
      },
      {
        "Name": "OnSyscall",
        "tg": 14000,
        "cg": 14000,
        "sg": 0,
        "tt": 0
      },
      {
        "Name": "OnBlockRead",
        "tg": 246,
        "cg": 246,
        "sg": 0,
        "tt": 0
      },
      {
        "Name": "wasm_exec",
        "tg": 190773,
        "cg": 190773,
        "sg": 0,
        "tt": 0
      },
      {
        "Name": "OnSyscall",
        "tg": 14000,
        "cg": 14000,
        "sg": 0,
        "tt": 0
      },
      {
        "Name": "OnBlockCreate",
        "tg": 160,
        "cg": 39,
        "sg": 122,
        "tt": 0
      },
      {
        "Name": "wasm_exec",
        "tg": 152,
        "cg": 152,
        "sg": 0,
        "tt": 0
      },
      {
        "Name": "OnSyscall",
        "tg": 14000,
        "cg": 14000,
        "sg": 0,
        "tt": 0
      },
      {
        "Name": "OnBlockLink",
        "tg": 559639,
        "cg": 199,
        "sg": 559440,
        "tt": 0
      },
      {
        "Name": "wasm_exec",
        "tg": 51368,
        "cg": 51368,
        "sg": 0,
        "tt": 0
      },
      {
        "Name": "OnSyscall",
        "tg": 14000,
        "cg": 14000,
        "sg": 0,
        "tt": 0
      },
      {
        "Name": "OnBlockCreate",
        "tg": 550,
        "cg": 132,
        "sg": 418,
        "tt": 0
      },
      {
        "Name": "wasm_exec",
        "tg": 152,
        "cg": 152,
        "sg": 0,
        "tt": 0
      },
      {
        "Name": "OnSyscall",
        "tg": 14000,
        "cg": 14000,
        "sg": 0,
        "tt": 0
      },
      {
        "Name": "OnBlockLink",
        "tg": 690382,
        "cg": 682,
        "sg": 689700,
        "tt": 0
      },
      {
        "Name": "wasm_exec",
        "tg": 205931,
        "cg": 205931,
        "sg": 0,
        "tt": 0
      },
      {
        "Name": "OnSyscall",
        "tg": 14000,
        "cg": 14000,
        "sg": 0,
        "tt": 0
      },
      {
        "Name": "OnBlockCreate",
        "tg": 6570,
        "cg": 1577,
        "sg": 4994,
        "tt": 0
      },
      {
        "Name": "wasm_exec",
        "tg": 152,
        "cg": 152,
        "sg": 0,
        "tt": 0
      },
      {
        "Name": "OnSyscall",
        "tg": 14000,
        "cg": 14000,
        "sg": 0,
        "tt": 0
      },
      {
        "Name": "OnBlockLink",
        "tg": 2708527,
        "cg": 8147,
        "sg": 2700380,
        "tt": 0
      },
      {
        "Name": "wasm_exec",
        "tg": 58832,
        "cg": 58832,
        "sg": 0,
        "tt": 0
      },
      {
        "Name": "OnSyscall",
        "tg": 14000,
        "cg": 14000,
        "sg": 0,
        "tt": 0
      },
      {
        "Name": "OnBlockCreate",
        "tg": 600,
        "cg": 144,
        "sg": 456,
        "tt": 0
      },
      {
        "Name": "wasm_exec",
        "tg": 152,
        "cg": 152,
        "sg": 0,
        "tt": 0
      },
      {
        "Name": "OnSyscall",
        "tg": 14000,
        "cg": 14000,
        "sg": 0,
        "tt": 0
      },
      {
        "Name": "OnBlockLink",
        "tg": 707144,
        "cg": 744,
        "sg": 706400,
        "tt": 0
      },
      {
        "Name": "wasm_exec",
        "tg": 177429,
        "cg": 177429,
        "sg": 0,
        "tt": 0
      },
      {
        "Name": "OnSyscall",
        "tg": 14000,
        "cg": 14000,
        "sg": 0,
        "tt": 0
      },
      {
        "Name": "OnBlockCreate",
        "tg": 3430,
        "cg": 824,
        "sg": 2607,
        "tt": 0
      },
      {
        "Name": "wasm_exec",
        "tg": 152,
        "cg": 152,
        "sg": 0,
        "tt": 0
      },
      {
        "Name": "OnSyscall",
        "tg": 14000,
        "cg": 14000,
        "sg": 0,
        "tt": 0
      },
      {
        "Name": "OnBlockLink",
        "tg": 1655874,
        "cg": 4254,
        "sg": 1651620,
        "tt": 0
      },
      {
        "Name": "wasm_exec",
        "tg": 7233,
        "cg": 7233,
        "sg": 0,
        "tt": 0
      },
      {
        "Name": "OnSyscall",
        "tg": 14000,
        "cg": 14000,
        "sg": 0,
        "tt": 0
      },
      {
        "Name": "OnActorUpdate",
        "tg": 475000,
        "cg": 0,
        "sg": 475000,
        "tt": 0
      },
      {
        "Name": "wasm_exec",
        "tg": 4616,
        "cg": 4616,
        "sg": 0,
        "tt": 0
      },
      {
        "Name": "OnSyscall",
        "tg": 14000,
        "cg": 14000,
        "sg": 0,
        "tt": 0
      },
      {
        "Name": "wasm_exec",
        "tg": 6555,
        "cg": 6555,
        "sg": 0,
        "tt": 0
      },
      {
        "Name": "OnSyscall",
        "tg": 14000,
        "cg": 14000,
        "sg": 0,
        "tt": 0
      },
      {
        "Name": "OnBlockOpenBase",
        "tg": 187440,
        "cg": 0,
        "sg": 187440,
        "tt": 0
      },
      {
        "Name": "OnBlockOpenPerByte",
        "tg": 3430,
        "cg": 824,
        "sg": 2607,
        "tt": 0
      },
      {
        "Name": "wasm_exec",
        "tg": 3156,
        "cg": 3156,
        "sg": 0,
        "tt": 0
      },
      {
        "Name": "OnSyscall",
        "tg": 14000,
        "cg": 14000,
        "sg": 0,
        "tt": 0
      },
      {
        "Name": "OnBlockRead",
        "tg": 138,
        "cg": 138,
        "sg": 0,
        "tt": 0
      },
      {
        "Name": "wasm_exec",
        "tg": 80969,
        "cg": 80969,
        "sg": 0,
        "tt": 0
      },
      {
        "Name": "OnSyscall",
        "tg": 14000,
        "cg": 14000,
        "sg": 0,
        "tt": 0
      },
      {
        "Name": "OnSelfBalance",
        "tg": 0,
        "cg": 0,
        "sg": 0,
        "tt": 0
      },
      {
        "Name": "wasm_exec",
        "tg": 34077,
        "cg": 34077,
        "sg": 0,
        "tt": 0
      }
    ],
    "Subcalls": [
      {
        "Msg": {
          "From": "f02620",
          "To": "f02",
          "Value": "0",
          "Method": 3,
          "Params": null,
          "ParamsCodec": 0
        },
        "MsgRct": {
          "ExitCode": 0,
          "Return": "goJYGgAEj122a9kP3EPZ5pH3Oz41Rg92i7+nC/02VwFKVMa54pdvxrRBou8pr9AjBEx7rq4fSQDxsZqEcuX/3Q==",
          "ReturnCodec": 0
        },
        "GasCharges": [
          {
            "Name": "OnMethodInvocation",
            "tg": 75000,
            "cg": 75000,
            "sg": 0,
            "tt": 0
          },
          {
            "Name": "wasm_memory_init",
            "tg": 445645,
            "cg": 445645,
            "sg": 0,
            "tt": 0
          },
          {
            "Name": "wasm_exec",
            "tg": 556,
            "cg": 556,
            "sg": 0,
            "tt": 0
          },
          {
            "Name": "OnSyscall",
            "tg": 14000,
            "cg": 14000,
            "sg": 0,
            "tt": 0
          },
          {
            "Name": "wasm_exec",
            "tg": 448,
            "cg": 448,
            "sg": 0,
            "tt": 0
          },
          {
            "Name": "OnSyscall",
            "tg": 14000,
            "cg": 14000,
            "sg": 0,
            "tt": 0
          },
          {
            "Name": "OnMessageContext",
            "tg": 0,
            "cg": 0,
            "sg": 0,
            "tt": 0
          },
          {
            "Name": "wasm_exec",
            "tg": 21124,
            "cg": 21124,
            "sg": 0,
            "tt": 0
          },
          {
            "Name": "wasm_memory_grow",
            "tg": 26215,
            "cg": 26215,
            "sg": 0,
            "tt": 0
          },
          {
            "Name": "OnSyscall",
            "tg": 14000,
            "cg": 14000,
            "sg": 0,
            "tt": 0
          },
          {
            "Name": "OnGetActorCodeCid",
            "tg": 0,
            "cg": 0,
            "sg": 0,
            "tt": 0
          },
          {
            "Name": "wasm_exec",
            "tg": 9701,
            "cg": 9701,
            "sg": 0,
            "tt": 0
          },
          {
            "Name": "OnSyscall",
            "tg": 14000,
            "cg": 14000,
            "sg": 0,
            "tt": 0
          },
          {
            "Name": "OnGetBuiltinActorType",
            "tg": 0,
            "cg": 0,
            "sg": 0,
            "tt": 0
          },
          {
            "Name": "wasm_exec",
            "tg": 1120,
            "cg": 1120,
            "sg": 0,
            "tt": 0
          },
          {
            "Name": "OnSyscall",
            "tg": 14000,
            "cg": 14000,
            "sg": 0,
            "tt": 0
          },
          {
            "Name": "wasm_exec",
            "tg": 7138,
            "cg": 7138,
            "sg": 0,
            "tt": 0
          },
          {
            "Name": "OnSyscall",
            "tg": 14000,
            "cg": 14000,
            "sg": 0,
            "tt": 0
          },
          {
            "Name": "OnBlockOpenBase",
            "tg": 187440,
            "cg": 0,
            "sg": 187440,
            "tt": 0
          },
          {
            "Name": "OnBlockOpenPerByte",
            "tg": 1620,
            "cg": 389,
            "sg": 1232,
            "tt": 0
          },
          {
            "Name": "wasm_exec",
            "tg": 1112,
            "cg": 1112,
            "sg": 0,
            "tt": 0
          },
          {
            "Name": "OnSyscall",
            "tg": 14000,
            "cg": 14000,
            "sg": 0,
            "tt": 0
          },
          {
            "Name": "OnBlockRead",
            "tg": 65,
            "cg": 65,
            "sg": 0,
            "tt": 0
          },
          {
            "Name": "wasm_exec",
            "tg": 140084,
            "cg": 140084,
            "sg": 0,
            "tt": 0
          },
          {
            "Name": "OnSyscall",
            "tg": 14000,
            "cg": 14000,
            "sg": 0,
            "tt": 0
          },
          {
            "Name": "OnBlockCreate",
            "tg": 640,
            "cg": 154,
            "sg": 487,
            "tt": 0
          },
          {
            "Name": "wasm_exec",
            "tg": 5264,
            "cg": 5264,
            "sg": 0,
            "tt": 0
          }
        ],
        "Subcalls": null
      },
      {
        "Msg": {
          "From": "f02620",
          "To": "f04",
          "Value": "0",
          "Method": 9,
          "Params": null,
          "ParamsCodec": 0
        },
        "MsgRct": {
          "ExitCode": 0,
          "Return": "hEkA0AukWAAAAABKAAE3F0XaKLoAAEwAc3KU08qYYfG0UgeCWBoAATcOA/6vRoNVIe1L2Qswhee5sQ/MAPLujFcAAmYelm8wR1sxMivq8YG2qntbhwBUdw==",
          "ReturnCodec": 0
        },
        "GasCharges": [
          {
            "Name": "OnMethodInvocation",
            "tg": 75000,
            "cg": 75000,
            "sg": 0,
            "tt": 0
          },
          {
            "Name": "wasm_memory_init",
            "tg": 445645,
            "cg": 445645,
            "sg": 0,
            "tt": 0
          },
          {
            "Name": "wasm_exec",
            "tg": 632,
            "cg": 632,
            "sg": 0,
            "tt": 0
          },
          {
            "Name": "OnSyscall",
            "tg": 14000,
            "cg": 14000,
            "sg": 0,
            "tt": 0
          },
          {
            "Name": "wasm_exec",
            "tg": 448,
            "cg": 448,
            "sg": 0,
            "tt": 0
          },
          {
            "Name": "OnSyscall",
            "tg": 14000,
            "cg": 14000,
            "sg": 0,
            "tt": 0
          },
          {
            "Name": "OnMessageContext",
            "tg": 0,
            "cg": 0,
            "sg": 0,
            "tt": 0
          },
          {
            "Name": "wasm_exec",
            "tg": 20960,
            "cg": 20960,
            "sg": 0,
            "tt": 0
          },
          {
            "Name": "wasm_memory_grow",
            "tg": 26215,
            "cg": 26215,
            "sg": 0,
            "tt": 0
          },
          {
            "Name": "OnSyscall",
            "tg": 14000,
            "cg": 14000,
            "sg": 0,
            "tt": 0
          },
          {
            "Name": "OnGetActorCodeCid",
            "tg": 0,
            "cg": 0,
            "sg": 0,
            "tt": 0
          },
          {
            "Name": "wasm_exec",
            "tg": 9701,
            "cg": 9701,
            "sg": 0,
            "tt": 0
          },
          {
            "Name": "OnSyscall",
            "tg": 14000,
            "cg": 14000,
            "sg": 0,
            "tt": 0
          },
          {
            "Name": "OnGetBuiltinActorType",
            "tg": 0,
            "cg": 0,
            "sg": 0,
            "tt": 0
          },
          {
            "Name": "wasm_exec",
            "tg": 1256,
            "cg": 1256,
            "sg": 0,
            "tt": 0
          },
          {
            "Name": "OnSyscall",
            "tg": 14000,
            "cg": 14000,
            "sg": 0,
            "tt": 0
          },
          {
            "Name": "wasm_exec",
            "tg": 6555,
            "cg": 6555,
            "sg": 0,
            "tt": 0
          },
          {
            "Name": "OnSyscall",
            "tg": 14000,
            "cg": 14000,
            "sg": 0,
            "tt": 0
          },
          {
            "Name": "OnBlockOpenBase",
            "tg": 187440,
            "cg": 0,
            "sg": 187440,
            "tt": 0
          },
          {
            "Name": "OnBlockOpenPerByte",
            "tg": 2850,
            "cg": 684,
            "sg": 2166,
            "tt": 0
          },
          {
            "Name": "wasm_exec",
            "tg": 1456,
            "cg": 1456,
            "sg": 0,
            "tt": 0
          },
          {
            "Name": "OnSyscall",
            "tg": 14000,
            "cg": 14000,
            "sg": 0,
            "tt": 0
          },
          {
            "Name": "OnBlockRead",
            "tg": 114,
            "cg": 114,
            "sg": 0,
            "tt": 0
          },
          {
            "Name": "wasm_exec",
            "tg": 189126,
            "cg": 189126,
            "sg": 0,
            "tt": 0
          },
          {
            "Name": "OnSyscall",
            "tg": 14000,
            "cg": 14000,
            "sg": 0,
            "tt": 0
          },
          {
            "Name": "OnBlockCreate",
            "tg": 880,
            "cg": 212,
            "sg": 669,
            "tt": 0
          },
          {
            "Name": "wasm_exec",
            "tg": 5568,
            "cg": 5568,
            "sg": 0,
            "tt": 0
          }
        ],
        "Subcalls": null
      },
      {
        "Msg": {
          "From": "f02620",
          "To": "f05",
          "Value": "0",
          "Method": 5,
          "Params": "gYGDCBoAQUqXhRoBzfAuGgHOHScaAc46thoBzjq3GgHOOrg=",
          "ParamsCodec": 0
        },
        "MsgRct": {
          "ExitCode": 0,
          "Return": "gYGB2CpYKAABgeIDkiAgw2gUc7MwFAwuYqGAqTBQaNScVS4bUoak9SImDgHQLzY=",
          "ReturnCodec": 0
        },
        "GasCharges": [
          {
            "Name": "OnMethodInvocation",
            "tg": 75000,
            "cg": 75000,
            "sg": 0,
            "tt": 0
          },
          {
            "Name": "wasm_memory_init",
            "tg": 445645,
            "cg": 445645,
            "sg": 0,
            "tt": 0
          },
          {
            "Name": "wasm_exec",
            "tg": 632,
            "cg": 632,
            "sg": 0,
            "tt": 0
          },
          {
            "Name": "OnSyscall",
            "tg": 14000,
            "cg": 14000,
            "sg": 0,
            "tt": 0
          },
          {
            "Name": "wasm_exec",
            "tg": 448,
            "cg": 448,
            "sg": 0,
            "tt": 0
          },
          {
            "Name": "OnSyscall",
            "tg": 14000,
            "cg": 14000,
            "sg": 0,
            "tt": 0
          },
          {
            "Name": "OnMessageContext",
            "tg": 0,
            "cg": 0,
            "sg": 0,
            "tt": 0
          },
          {
            "Name": "wasm_exec",
            "tg": 395,
            "cg": 395,
            "sg": 0,
            "tt": 0
          },
          {
            "Name": "OnSyscall",
            "tg": 14000,
            "cg": 14000,
            "sg": 0,
            "tt": 0
          },
          {
            "Name": "OnBlockStat",
            "tg": 0,
            "cg": 0,
            "sg": 0,
            "tt": 0
          },
          {
            "Name": "wasm_exec",
            "tg": 4076,
            "cg": 4076,
            "sg": 0,
            "tt": 0
          },
          {
            "Name": "wasm_memory_grow",
            "tg": 26215,
            "cg": 26215,
            "sg": 0,
            "tt": 0
          },
          {
            "Name": "OnSyscall",
            "tg": 14000,
            "cg": 14000,
            "sg": 0,
            "tt": 0
          },
          {
            "Name": "OnBlockRead",
            "tg": 14,
            "cg": 14,
            "sg": 0,
            "tt": 0
          },
          {
            "Name": "wasm_exec",
            "tg": 18034,
            "cg": 18034,
            "sg": 0,
            "tt": 0
          },
          {
            "Name": "OnSyscall",
            "tg": 14000,
            "cg": 14000,
            "sg": 0,
            "tt": 0
          },
          {
            "Name": "OnGetActorCodeCid",
            "tg": 0,
            "cg": 0,
            "sg": 0,
            "tt": 0
          },
          {
            "Name": "wasm_exec",
            "tg": 9701,
            "cg": 9701,
            "sg": 0,
            "tt": 0
          },
          {
            "Name": "OnSyscall",
            "tg": 14000,
            "cg": 14000,
            "sg": 0,
            "tt": 0
          },
          {
            "Name": "OnGetBuiltinActorType",
            "tg": 0,
            "cg": 0,
            "sg": 0,
            "tt": 0
          },
          {
            "Name": "wasm_exec",
            "tg": 14966,
            "cg": 14966,
            "sg": 0,
            "tt": 0
          },
          {
            "Name": "OnSyscall",
            "tg": 14000,
            "cg": 14000,
            "sg": 0,
            "tt": 0
          },
          {
            "Name": "OnGetActorCodeCid",
            "tg": 0,
            "cg": 0,
            "sg": 0,
            "tt": 0
          },
          {
            "Name": "wasm_exec",
            "tg": 9701,
            "cg": 9701,
            "sg": 0,
            "tt": 0
          },
          {
            "Name": "OnSyscall",
            "tg": 14000,
            "cg": 14000,
            "sg": 0,
            "tt": 0
          },
          {
            "Name": "OnGetBuiltinActorType",
            "tg": 0,
            "cg": 0,
            "sg": 0,
            "tt": 0
          },
          {
            "Name": "wasm_exec",
            "tg": 1688,
            "cg": 1688,
            "sg": 0,
            "tt": 0
          },
          {
            "Name": "OnSyscall",
            "tg": 14000,
            "cg": 14000,
            "sg": 0,
            "tt": 0
          },
          {
            "Name": "OnNetworkContext",
            "tg": 0,
            "cg": 0,
            "sg": 0,
            "tt": 0
          },
          {
            "Name": "wasm_exec",
            "tg": 560,
            "cg": 560,
            "sg": 0,
            "tt": 0
          },
          {
            "Name": "OnSyscall",
            "tg": 14000,
            "cg": 14000,
            "sg": 0,
            "tt": 0
          },
          {
            "Name": "wasm_exec",
            "tg": 6555,
            "cg": 6555,
            "sg": 0,
            "tt": 0
          },
          {
            "Name": "OnSyscall",
            "tg": 14000,
            "cg": 14000,
            "sg": 0,
            "tt": 0
          },
          {
            "Name": "OnBlockOpenBase",
            "tg": 187440,
            "cg": 0,
            "sg": 187440,
            "tt": 0
          },
          {
            "Name": "OnBlockOpenPerByte",
            "tg": 3360,
            "cg": 807,
            "sg": 2554,
            "tt": 0
          },
          {
            "Name": "wasm_exec",
            "tg": 1456,
            "cg": 1456,
            "sg": 0,
            "tt": 0
          },
          {
            "Name": "OnSyscall",
            "tg": 14000,
            "cg": 14000,
            "sg": 0,
            "tt": 0
          },
          {
            "Name": "OnBlockRead",
            "tg": 135,
            "cg": 135,
            "sg": 0,
            "tt": 0
          },
          {
            "Name": "wasm_exec",
            "tg": 73028,
            "cg": 73028,
            "sg": 0,
            "tt": 0
          },
          {
            "Name": "OnSyscall",
            "tg": 14000,
            "cg": 14000,
            "sg": 0,
            "tt": 0
          },
          {
            "Name": "OnBlockOpenBase",
            "tg": 187440,
            "cg": 0,
            "sg": 187440,
            "tt": 0
          },
          {
            "Name": "OnBlockOpenPerByte",
            "tg": 12210,
            "cg": 2931,
            "sg": 9280,
            "tt": 0
          },
          {
            "Name": "wasm_exec",
            "tg": 1756,
            "cg": 1756,
            "sg": 0,
            "tt": 0
          },
          {
            "Name": "OnSyscall",
            "tg": 14000,
            "cg": 14000,
            "sg": 0,
            "tt": 0
          },
          {
            "Name": "OnBlockRead",
            "tg": 489,
            "cg": 489,
            "sg": 0,
            "tt": 0
          },
          {
            "Name": "wasm_exec",
            "tg": 229532,
            "cg": 229532,
            "sg": 0,
            "tt": 0
          },
          {
            "Name": "OnSyscall",
            "tg": 14000,
            "cg": 14000,
            "sg": 0,
            "tt": 0
          },
          {
            "Name": "OnBlockOpenBase",
            "tg": 187440,
            "cg": 0,
            "sg": 187440,
            "tt": 0
          },
          {
            "Name": "OnBlockOpenPerByte",
            "tg": 12990,
            "cg": 3118,
            "sg": 9873,
            "tt": 0
          },
          {
            "Name": "wasm_exec",
            "tg": 3132,
            "cg": 3132,
            "sg": 0,
            "tt": 0
          },
          {
            "Name": "OnSyscall",
            "tg": 14000,
            "cg": 14000,
            "sg": 0,
            "tt": 0
          },
          {
            "Name": "OnBlockRead",
            "tg": 520,
            "cg": 520,
            "sg": 0,
            "tt": 0
          },
          {
            "Name": "wasm_exec",
            "tg": 238589,
            "cg": 238589,
            "sg": 0,
            "tt": 0
          },
          {
            "Name": "OnSyscall",
            "tg": 14000,
            "cg": 14000,
            "sg": 0,
            "tt": 0
          },
          {
            "Name": "OnBlockOpenBase",
            "tg": 187440,
            "cg": 0,
            "sg": 187440,
            "tt": 0
          },
          {
            "Name": "OnBlockOpenPerByte",
            "tg": 13850,
            "cg": 3324,
            "sg": 10526,
            "tt": 0
          },
          {
            "Name": "wasm_exec",
            "tg": 1756,
            "cg": 1756,
            "sg": 0,
            "tt": 0
          },
          {
            "Name": "OnSyscall",
            "tg": 14000,
            "cg": 14000,
            "sg": 0,
            "tt": 0
          },
          {
            "Name": "OnBlockRead",
            "tg": 554,
            "cg": 554,
            "sg": 0,
            "tt": 0
          },
          {
            "Name": "wasm_exec",
            "tg": 251718,
            "cg": 251718,
            "sg": 0,
            "tt": 0
          },
          {
            "Name": "OnSyscall",
            "tg": 14000,
            "cg": 14000,
            "sg": 0,
            "tt": 0
          },
          {
            "Name": "OnBlockOpenBase",
            "tg": 187440,
            "cg": 0,
            "sg": 187440,
            "tt": 0
          },
          {
            "Name": "OnBlockOpenPerByte",
            "tg": 13850,
            "cg": 3324,
            "sg": 10526,
            "tt": 0
          },
          {
            "Name": "wasm_exec",
            "tg": 3132,
            "cg": 3132,
            "sg": 0,
            "tt": 0
          },
          {
            "Name": "OnSyscall",
            "tg": 14000,
            "cg": 14000,
            "sg": 0,
            "tt": 0
          },
          {
            "Name": "OnBlockRead",
            "tg": 554,
            "cg": 554,
            "sg": 0,
            "tt": 0
          },
          {
            "Name": "wasm_exec",
            "tg": 252714,
            "cg": 252714,
            "sg": 0,
            "tt": 0
          },
          {
            "Name": "OnSyscall",
            "tg": 14000,
            "cg": 14000,
            "sg": 0,
            "tt": 0
          },
          {
            "Name": "OnBlockOpenBase",
            "tg": 187440,
            "cg": 0,
            "sg": 187440,
            "tt": 0
          },
          {
            "Name": "OnBlockOpenPerByte",
            "tg": 46390,
            "cg": 11134,
            "sg": 35257,
            "tt": 0
          },
          {
            "Name": "wasm_exec",
            "tg": 2164,
            "cg": 2164,
            "sg": 0,
            "tt": 0
          },
          {
            "Name": "OnSyscall",
            "tg": 14000,
            "cg": 14000,
            "sg": 0,
            "tt": 0
          },
          {
            "Name": "OnBlockRead",
            "tg": 1856,
            "cg": 1856,
            "sg": 0,
            "tt": 0
          },
          {
            "Name": "wasm_exec",
            "tg": 1151751,
            "cg": 1151751,
            "sg": 0,
            "tt": 0
          },
          {
            "Name": "OnSyscall",
            "tg": 14000,
            "cg": 14000,
            "sg": 0,
            "tt": 0
          },
          {
            "Name": "OnBlockOpenBase",
            "tg": 187440,
            "cg": 0,
            "sg": 187440,
            "tt": 0
          },
          {
            "Name": "OnBlockOpenPerByte",
            "tg": 13850,
            "cg": 3324,
            "sg": 10526,
            "tt": 0
          },
          {
            "Name": "wasm_exec",
            "tg": 2412,
            "cg": 2412,
            "sg": 0,
            "tt": 0
          },
          {
            "Name": "OnSyscall",
            "tg": 14000,
            "cg": 14000,
            "sg": 0,
            "tt": 0
          },
          {
            "Name": "OnBlockRead",
            "tg": 554,
            "cg": 554,
            "sg": 0,
            "tt": 0
          },
          {
            "Name": "wasm_exec",
            "tg": 253422,
            "cg": 253422,
            "sg": 0,
            "tt": 0
          },
          {
            "Name": "OnSyscall",
            "tg": 14000,
            "cg": 14000,
            "sg": 0,
            "tt": 0
          },
          {
            "Name": "OnBlockOpenBase",
            "tg": 187440,
            "cg": 0,
            "sg": 187440,
            "tt": 0
          },
          {
            "Name": "OnBlockOpenPerByte",
            "tg": 13850,
            "cg": 3324,
            "sg": 10526,
            "tt": 0
          },
          {
            "Name": "wasm_exec",
            "tg": 2412,
            "cg": 2412,
            "sg": 0,
            "tt": 0
          },
          {
            "Name": "OnSyscall",
            "tg": 14000,
            "cg": 14000,
            "sg": 0,
            "tt": 0
          },
          {
            "Name": "OnBlockRead",
            "tg": 554,
            "cg": 554,
            "sg": 0,
            "tt": 0
          },
          {
            "Name": "wasm_exec",
            "tg": 253042,
            "cg": 253042,
            "sg": 0,
            "tt": 0
          },
          {
            "Name": "OnSyscall",
            "tg": 14000,
            "cg": 14000,
            "sg": 0,
            "tt": 0
          },
          {
            "Name": "OnBlockOpenBase",
            "tg": 187440,
            "cg": 0,
            "sg": 187440,
            "tt": 0
          },
          {
            "Name": "OnBlockOpenPerByte",
            "tg": 45220,
            "cg": 10853,
            "sg": 34368,
            "tt": 0
          },
          {
            "Name": "wasm_exec",
            "tg": 3132,
            "cg": 3132,
            "sg": 0,
            "tt": 0
          },
          {
            "Name": "OnSyscall",
            "tg": 14000,
            "cg": 14000,
            "sg": 0,
            "tt": 0
          },
          {
            "Name": "OnBlockRead",
            "tg": 1809,
            "cg": 1809,
            "sg": 0,
            "tt": 0
          },
          {
            "Name": "wasm_exec",
            "tg": 1154924,
            "cg": 1154924,
            "sg": 0,
            "tt": 0
          },
          {
            "Name": "wasm_memory_grow",
            "tg": 26215,
            "cg": 26215,
            "sg": 0,
            "tt": 0
          },
          {
            "Name": "OnSyscall",
            "tg": 14000,
            "cg": 14000,
            "sg": 0,
            "tt": 0
          },
          {
            "Name": "OnBlockOpenBase",
            "tg": 187440,
            "cg": 0,
            "sg": 187440,
            "tt": 0
          },
          {
            "Name": "OnBlockOpenPerByte",
            "tg": 13850,
            "cg": 3324,
            "sg": 10526,
            "tt": 0
          },
          {
            "Name": "wasm_exec",
            "tg": 3132,
            "cg": 3132,
            "sg": 0,
            "tt": 0
          },
          {
            "Name": "OnSyscall",
            "tg": 14000,
            "cg": 14000,
            "sg": 0,
            "tt": 0
          },
          {
            "Name": "OnBlockRead",
            "tg": 554,
            "cg": 554,
            "sg": 0,
            "tt": 0
          },
          {
            "Name": "wasm_exec",
            "tg": 256150,
            "cg": 256150,
            "sg": 0,
            "tt": 0
          },
          {
            "Name": "OnSyscall",
            "tg": 14000,
            "cg": 14000,
            "sg": 0,
            "tt": 0
          },
          {
            "Name": "OnBlockOpenBase",
            "tg": 187440,
            "cg": 0,
            "sg": 187440,
            "tt": 0
          },
          {
            "Name": "OnBlockOpenPerByte",
            "tg": 44980,
            "cg": 10796,
            "sg": 34185,
            "tt": 0
          },
          {
            "Name": "wasm_exec",
            "tg": 3424,
            "cg": 3424,
            "sg": 0,
            "tt": 0
          },
          {
            "Name": "OnSyscall",
            "tg": 14000,
            "cg": 14000,
            "sg": 0,
            "tt": 0
          },
          {
            "Name": "OnBlockRead",
            "tg": 1800,
            "cg": 1800,
            "sg": 0,
            "tt": 0
          },
          {
            "Name": "wasm_exec",
            "tg": 1268347,
            "cg": 1268347,
            "sg": 0,
            "tt": 0
          },
          {
            "Name": "OnSyscall",
            "tg": 14000,
            "cg": 14000,
            "sg": 0,
            "tt": 0
          },
          {
            "Name": "OnComputeUnsealedSectorCid",
            "tg": 98647,
            "cg": 98647,
            "sg": 0,
            "tt": 0
          },
          {
            "Name": "wasm_exec",
            "tg": 467901,
            "cg": 467901,
            "sg": 0,
            "tt": 0
          },
          {
            "Name": "OnSyscall",
            "tg": 14000,
            "cg": 14000,
            "sg": 0,
            "tt": 0
          },
          {
            "Name": "OnBlockCreate",
            "tg": 470,
            "cg": 113,
            "sg": 358,
            "tt": 0
          },
          {
            "Name": "wasm_exec",
            "tg": 5816,
            "cg": 5816,
            "sg": 0,
            "tt": 0
          }
        ],
        "Subcalls": null
      }
    ]
  },
  "Error": "",
  "Duration": 4104220
}
